MANIFEST.in
README.rst
setup.py
cyckei/__init__.py
cyckei/cyckei.py
cyckei/__pycache__/__init__.cpython-38.pyc
cyckei/__pycache__/cyckei.cpython-38.pyc
cyckei/assets/bolt.png
cyckei/assets/default_config.json
cyckei/assets/default_packet.json
cyckei/assets/example-script
cyckei/assets/icon-client.png
cyckei/assets/icon-explorer.png
cyckei/assets/startup.lua
cyckei/assets/variables.json
cyckei/client/channel_tab.py
cyckei/client/client.py
cyckei/client/scripts.py
cyckei/client/socket.py
cyckei/client/workers.py
cyckei/client/__pycache__/__init__.cpython-38.pyc
cyckei/client/__pycache__/channel_tab.cpython-38.pyc
cyckei/client/__pycache__/client.cpython-38.pyc
cyckei/client/__pycache__/functions.cpython-38.pyc
cyckei/client/__pycache__/socket.cpython-38.pyc
cyckei/client/__pycache__/workers.cpython-38.pyc
cyckei/explorer/explorer.py
cyckei/explorer/log_viewer.py
cyckei/explorer/script_editor.py
cyckei/explorer/workers.py
cyckei/explorer/__pycache__/__init__.cpython-38.pyc
cyckei/explorer/__pycache__/explorer.cpython-38.pyc
cyckei/explorer/__pycache__/functions.cpython-38.pyc
cyckei/explorer/__pycache__/log_viewer.cpython-38.pyc
cyckei/explorer/__pycache__/script_editor.cpython-38.pyc
cyckei/explorer/__pycache__/scripts.cpython-38.pyc
cyckei/explorer/__pycache__/workers.cpython-38.pyc
cyckei/functions/func.py
cyckei/functions/gui.py
cyckei/functions/__pycache__/__init__.cpython-38.pyc
cyckei/functions/__pycache__/func.cpython-38.pyc
cyckei/functions/__pycache__/gui.cpython-38.pyc
cyckei/server/models.py
cyckei/server/protocols.py
cyckei/server/server.py
cyckei/server/__pycache__/__init__.cpython-38.pyc
cyckei/server/__pycache__/models.cpython-38.pyc
cyckei/server/__pycache__/protocols.cpython-38.pyc
cyckei/server/__pycache__/server.cpython-38.pyc
cyckei/tests/test_config.json
cyckei/tests/test_keithley.py