Metadata-Version: 2.1
Name: cyckei
Version: 0.3.dev1
Summary: Keithley Battery Cycler for Python 3
Home-page: https://gitlab.com/cyclikal/cyckei
Author: Cyclikal, LLC
Author-email: gabriel@cyclikal.com
License: UNKNOWN
Keywords: keithley battery lithium-ion cycling calorimetry
Platform: UNKNOWN
Classifier: Programming Language :: Python :: 3
Classifier: License :: OSI Approved :: GNU General Public License v3 (GPLv3)
Classifier: Operating System :: OS Independent
Classifier: Topic :: Scientific/Engineering
